{"nodes": [{"id": "backend_app_services_embeddings_py", "label": "embeddings.py", "file_type": "code", "source_file": "backend/app/services/embeddings.py", "source_location": "L1"}, {"id": "embeddings_serverless_mode", "label": "_serverless_mode()", "file_type": "code", "source_file": "backend/app/services/embeddings.py", "source_location": "L26"}, {"id": "embeddings_get_semantic_model", "label": "_get_semantic_model()", "file_type": "code", "source_file": "backend/app/services/embeddings.py", "source_location": "L37"}, {"id": "embeddings_embeddingservice", "label": "EmbeddingService", "file_type": "code", "source_file": "backend/app/services/embeddings.py", "source_location": "L66"}, {"id": "embeddings_embeddingservice_init", "label": ".__init__()", "file_type": "code", "source_file": "backend/app/services/embeddings.py", "source_location": "L67"}, {"id": "embeddings_semantic_available", "label": "semantic_available()", "file_type": "code", "source_file": "backend/app/services/embeddings.py", "source_location": "L81"}, {"id": "embeddings_backend_name", "label": "backend_name()", "file_type": "code", "source_file": "backend/app/services/embeddings.py", "source_location": "L85"}, {"id": "embeddings_embeddingservice_embed_texts", "label": ".embed_texts()", "file_type": "code", "source_file": "backend/app/services/embeddings.py", "source_location": "L88"}, {"id": "embeddings_embeddingservice_should_persist_replacement", "label": ".should_persist_replacement()", "file_type": "code", "source_file": "backend/app/services/embeddings.py", "source_location": "L137"}, {"id": "embeddings_embeddingservice_load_cached_embedding", "label": "._load_cached_embedding()", "file_type": "code", "source_file": "backend/app/services/embeddings.py", "source_location": "L141"}, {"id": "embeddings_embeddingservice_embed_local", "label": ".embed_local()", "file_type": "code", "source_file": "backend/app/services/embeddings.py", "source_location": "L154"}, {"id": "embeddings_embeddingservice_embed_semantic", "label": ".embed_semantic()", "file_type": "code", "source_file": "backend/app/services/embeddings.py", "source_location": "L164"}, {"id": "embeddings_embeddingservice_hash_embed", "label": "._hash_embed()", "file_type": "code", "source_file": "backend/app/services/embeddings.py", "source_location": "L196"}, {"id": "embeddings_embeddingservice_normalize", "label": "._normalize()", "file_type": "code", "source_file": "backend/app/services/embeddings.py", "source_location": "L210"}, {"id": "embeddings_embeddingservice_hash_text", "label": "._hash_text()", "file_type": "code", "source_file": "backend/app/services/embeddings.py", "source_location": "L216"}, {"id": "embeddings_rationale_38", "label": "Lazy-load sentence-transformers. Returns None when unavailable so     EmbeddingS", "file_type": "rationale", "source_file": "backend/app/services/embeddings.py", "source_location": "L38"}, {"id": "embeddings_rationale_155", "label": "Uncached embedding generation \u2014 used by scoring paths that don't         need DB", "file_type": "rationale", "source_file": "backend/app/services/embeddings.py", "source_location": "L155"}, {"id": "embeddings_rationale_165", "label": "Return normalized sentence-transformer vectors, never hash vectors.", "file_type": "rationale", "source_file": "backend/app/services/embeddings.py", "source_location": "L165"}], "edges": [{"source": "backend_app_services_embeddings_py", "target": "hashlib", "relation": "imports", "confidence": "EXTRACTED", "source_file": "backend/app/services/embeddings.py", "source_location": "L1", "weight": 1.0}, {"source": "backend_app_services_embeddings_py", "target": "json", "relation": "imports", "confidence": "EXTRACTED", "source_file": "backend/app/services/embeddings.py", "source_location": "L2", "weight": 1.0}, {"source": "backend_app_services_embeddings_py", "target": "logging", "relation": "imports", "confidence": "EXTRACTED", "source_file": "backend/app/services/embeddings.py", "source_location": "L3", "weight": 1.0}, {"source": "backend_app_services_embeddings_py", "target": "os", "relation": "imports", "confidence": "EXTRACTED", "source_file": "backend/app/services/embeddings.py", "source_location": "L4", "weight": 1.0}, {"source": "backend_app_services_embeddings_py", "target": "threading", "relation": "imports", "confidence": "EXTRACTED", "source_file": "backend/app/services/embeddings.py", "source_location": "L5", "weight": 1.0}, {"source": "backend_app_services_embeddings_py", "target": "typing", "relation": "imports_from", "confidence": "EXTRACTED", "source_file": "backend/app/services/embeddings.py", "source_location": "L6", "weight": 1.0}, {"source": "backend_app_services_embeddings_py", "target": "numpy", "relation": "imports", "confidence": "EXTRACTED", "source_file": "backend/app/services/embeddings.py", "source_location": "L8", "weight": 1.0}, {"source": "backend_app_services_embeddings_py", "target": "backend_app_db_py", "relation": "imports_from", "confidence": "EXTRACTED", "source_file": "backend/app/services/embeddings.py", "source_location": "L10", "weight": 1.0}, {"source": "backend_app_services_embeddings_py", "target": "embeddings_serverless_mode", "relation": "contains", "confidence": "EXTRACTED", "source_file": "backend/app/services/embeddings.py", "source_location": "L26", "weight": 1.0}, {"source": "backend_app_services_embeddings_py", "target": "embeddings_get_semantic_model", "relation": "contains", "confidence": "EXTRACTED", "source_file": "backend/app/services/embeddings.py", "source_location": "L37", "weight": 1.0}, {"source": "backend_app_services_embeddings_py", "target": "embeddings_embeddingservice", "relation": "contains", "confidence": "EXTRACTED", "source_file": "backend/app/services/embeddings.py", "source_location": "L66", "weight": 1.0}, {"source": "embeddings_embeddingservice", "target": "embeddings_embeddingservice_init", "relation": "method", "confidence": "EXTRACTED", "source_file": "backend/app/services/embeddings.py", "source_location": "L67", "weight": 1.0}, {"source": "backend_app_services_embeddings_py", "target": "embeddings_semantic_available", "relation": "contains", "confidence": "EXTRACTED", "source_file": "backend/app/services/embeddings.py", "source_location": "L81", "weight": 1.0}, {"source": "backend_app_services_embeddings_py", "target": "embeddings_backend_name", "relation": "contains", "confidence": "EXTRACTED", "source_file": "backend/app/services/embeddings.py", "source_location": "L85", "weight": 1.0}, {"source": "embeddings_embeddingservice", "target": "embeddings_embeddingservice_embed_texts", "relation": "method", "confidence": "EXTRACTED", "source_file": "backend/app/services/embeddings.py", "source_location": "L88", "weight": 1.0}, {"source": "embeddings_embeddingservice", "target": "embeddings_embeddingservice_should_persist_replacement", "relation": "method", "confidence": "EXTRACTED", "source_file": "backend/app/services/embeddings.py", "source_location": "L137", "weight": 1.0}, {"source": "embeddings_embeddingservice", "target": "embeddings_embeddingservice_load_cached_embedding", "relation": "method", "confidence": "EXTRACTED", "source_file": "backend/app/services/embeddings.py", "source_location": "L141", "weight": 1.0}, {"source": "embeddings_embeddingservice", "target": "embeddings_embeddingservice_embed_local", "relation": "method", "confidence": "EXTRACTED", "source_file": "backend/app/services/embeddings.py", "source_location": "L154", "weight": 1.0}, {"source": "embeddings_embeddingservice", "target": "embeddings_embeddingservice_embed_semantic", "relation": "method", "confidence": "EXTRACTED", "source_file": "backend/app/services/embeddings.py", "source_location": "L164", "weight": 1.0}, {"source": "embeddings_embeddingservice", "target": "embeddings_embeddingservice_embed_local", "relation": "method", "confidence": "EXTRACTED", "source_file": "backend/app/services/embeddings.py", "source_location": "L184", "weight": 1.0}, {"source": "embeddings_embeddingservice", "target": "embeddings_embeddingservice_hash_embed", "relation": "method", "confidence": "EXTRACTED", "source_file": "backend/app/services/embeddings.py", "source_location": "L196", "weight": 1.0}, {"source": "embeddings_embeddingservice", "target": "embeddings_embeddingservice_normalize", "relation": "method", "confidence": "EXTRACTED", "source_file": "backend/app/services/embeddings.py", "source_location": "L210", "weight": 1.0}, {"source": "embeddings_embeddingservice", "target": "embeddings_embeddingservice_hash_text", "relation": "method", "confidence": "EXTRACTED", "source_file": "backend/app/services/embeddings.py", "source_location": "L216", "weight": 1.0}, {"source": "embeddings_get_semantic_model", "target": "embeddings_serverless_mode", "relation": "calls", "confidence": "EXTRACTED", "source_file": "backend/app/services/embeddings.py", "source_location": "L44", "weight": 1.0}, {"source": "embeddings_embeddingservice_init", "target": "embeddings_get_semantic_model", "relation": "calls", "confidence": "EXTRACTED", "source_file": "backend/app/services/embeddings.py", "source_location": "L72", "weight": 1.0}, {"source": "embeddings_embeddingservice_embed_texts", "target": "embeddings_embeddingservice_hash_text", "relation": "calls", "confidence": "EXTRACTED", "source_file": "backend/app/services/embeddings.py", "source_location": "L93", "weight": 1.0}, {"source": "embeddings_embeddingservice_embed_texts", "target": "embeddings_embeddingservice_load_cached_embedding", "relation": "calls", "confidence": "EXTRACTED", "source_file": "backend/app/services/embeddings.py", "source_location": "L101", "weight": 1.0}, {"source": "embeddings_embeddingservice_embed_texts", "target": "embeddings_embeddingservice_normalize", "relation": "calls", "confidence": "EXTRACTED", "source_file": "backend/app/services/embeddings.py", "source_location": "L117", "weight": 1.0}, {"source": "embeddings_embeddingservice_should_persist_replacement", "target": "embeddings_embeddingservice_load_cached_embedding", "relation": "calls", "confidence": "EXTRACTED", "source_file": "backend/app/services/embeddings.py", "source_location": "L138", "weight": 1.0}, {"source": "embeddings_embeddingservice_load_cached_embedding", "target": "embeddings_embeddingservice_normalize", "relation": "calls", "confidence": "EXTRACTED", "source_file": "backend/app/services/embeddings.py", "source_location": "L151", "weight": 1.0}, {"source": "embeddings_embeddingservice_embed_local", "target": "embeddings_embeddingservice_embed_semantic", "relation": "calls", "confidence": "EXTRACTED", "source_file": "backend/app/services/embeddings.py", "source_location": "L185", "weight": 1.0}, {"source": "embeddings_embeddingservice_embed_local", "target": "embeddings_embeddingservice_hash_embed", "relation": "calls", "confidence": "EXTRACTED", "source_file": "backend/app/services/embeddings.py", "source_location": "L193", "weight": 1.0}, {"source": "embeddings_embeddingservice_hash_embed", "target": "embeddings_embeddingservice_normalize", "relation": "calls", "confidence": "EXTRACTED", "source_file": "backend/app/services/embeddings.py", "source_location": "L208", "weight": 1.0}, {"source": "embeddings_rationale_38", "target": "embeddings_get_semantic_model", "relation": "rationale_for", "confidence": "EXTRACTED", "source_file": "backend/app/services/embeddings.py", "source_location": "L38", "weight": 1.0}, {"source": "embeddings_rationale_155", "target": "embeddings_embeddingservice_embed_local", "relation": "rationale_for", "confidence": "EXTRACTED", "source_file": "backend/app/services/embeddings.py", "source_location": "L155", "weight": 1.0}, {"source": "embeddings_rationale_165", "target": "embeddings_embeddingservice_embed_semantic", "relation": "rationale_for", "confidence": "EXTRACTED", "source_file": "backend/app/services/embeddings.py", "source_location": "L165", "weight": 1.0}]}