{"nodes": [{"id": "src_lib_historystorage_ts", "label": "historyStorage.ts", "file_type": "code", "source_file": "src/lib/historyStorage.ts", "source_location": "L1"}, {"id": "historystorage_normalizehistoryaccountid", "label": "normalizeHistoryAccountId()", "file_type": "code", "source_file": "src/lib/historyStorage.ts", "source_location": "L23"}, {"id": "historystorage_historyscopestoragekey", "label": "historyScopeStorageKey()", "file_type": "code", "source_file": "src/lib/historyStorage.ts", "source_location": "L28"}, {"id": "historystorage_seedguesthistoryscopefromactivehistory", "label": "seedGuestHistoryScopeFromActiveHistory()", "file_type": "code", "source_file": "src/lib/historyStorage.ts", "source_location": "L32"}, {"id": "historystorage_normalizestoredhistoryitem", "label": "normalizeStoredHistoryItem()", "file_type": "code", "source_file": "src/lib/historyStorage.ts", "source_location": "L48"}, {"id": "historystorage_normalizestoredhistoryitems", "label": "normalizeStoredHistoryItems()", "file_type": "code", "source_file": "src/lib/historyStorage.ts", "source_location": "L74"}, {"id": "historystorage_readscopedhistorysnapshot", "label": "readScopedHistorySnapshot()", "file_type": "code", "source_file": "src/lib/historyStorage.ts", "source_location": "L81"}, {"id": "historystorage_writescopedhistorysnapshot", "label": "writeScopedHistorySnapshot()", "file_type": "code", "source_file": "src/lib/historyStorage.ts", "source_location": "L100"}], "edges": [{"source": "src_lib_historystorage_ts", "target": "historystorage_normalizehistoryaccountid", "relation": "contains", "confidence": "EXTRACTED", "source_file": "src/lib/historyStorage.ts", "source_location": "L23", "weight": 1.0}, {"source": "src_lib_historystorage_ts", "target": "historystorage_historyscopestoragekey", "relation": "contains", "confidence": "EXTRACTED", "source_file": "src/lib/historyStorage.ts", "source_location": "L28", "weight": 1.0}, {"source": "src_lib_historystorage_ts", "target": "historystorage_seedguesthistoryscopefromactivehistory", "relation": "contains", "confidence": "EXTRACTED", "source_file": "src/lib/historyStorage.ts", "source_location": "L32", "weight": 1.0}, {"source": "src_lib_historystorage_ts", "target": "historystorage_normalizestoredhistoryitem", "relation": "contains", "confidence": "EXTRACTED", "source_file": "src/lib/historyStorage.ts", "source_location": "L48", "weight": 1.0}, {"source": "src_lib_historystorage_ts", "target": "historystorage_normalizestoredhistoryitems", "relation": "contains", "confidence": "EXTRACTED", "source_file": "src/lib/historyStorage.ts", "source_location": "L74", "weight": 1.0}, {"source": "src_lib_historystorage_ts", "target": "historystorage_readscopedhistorysnapshot", "relation": "contains", "confidence": "EXTRACTED", "source_file": "src/lib/historyStorage.ts", "source_location": "L81", "weight": 1.0}, {"source": "src_lib_historystorage_ts", "target": "historystorage_writescopedhistorysnapshot", "relation": "contains", "confidence": "EXTRACTED", "source_file": "src/lib/historyStorage.ts", "source_location": "L100", "weight": 1.0}, {"source": "historystorage_historyscopestoragekey", "target": "historystorage_normalizehistoryaccountid", "relation": "calls", "confidence": "EXTRACTED", "source_file": "src/lib/historyStorage.ts", "source_location": "L29", "weight": 1.0}, {"source": "historystorage_seedguesthistoryscopefromactivehistory", "target": "historystorage_historyscopestoragekey", "relation": "calls", "confidence": "EXTRACTED", "source_file": "src/lib/historyStorage.ts", "source_location": "L41", "weight": 1.0}, {"source": "historystorage_readscopedhistorysnapshot", "target": "historystorage_normalizehistoryaccountid", "relation": "calls", "confidence": "EXTRACTED", "source_file": "src/lib/historyStorage.ts", "source_location": "L86", "weight": 1.0}, {"source": "historystorage_readscopedhistorysnapshot", "target": "historystorage_historyscopestoragekey", "relation": "calls", "confidence": "EXTRACTED", "source_file": "src/lib/historyStorage.ts", "source_location": "L87", "weight": 1.0}, {"source": "historystorage_readscopedhistorysnapshot", "target": "historystorage_seedguesthistoryscopefromactivehistory", "relation": "calls", "confidence": "EXTRACTED", "source_file": "src/lib/historyStorage.ts", "source_location": "L94", "weight": 1.0}, {"source": "historystorage_writescopedhistorysnapshot", "target": "historystorage_historyscopestoragekey", "relation": "calls", "confidence": "EXTRACTED", "source_file": "src/lib/historyStorage.ts", "source_location": "L105", "weight": 1.0}]}